dagster_ext/__init__.py
dagster_ext/version.py
dagster_ext_process-1.4.17.dist-info/LICENSE
dagster_ext_process-1.4.17.dist-info/METADATA
dagster_ext_process-1.4.17.dist-info/WHEEL
dagster_ext_process-1.4.17.dist-info/entry_points.txt
dagster_ext_process-1.4.17.dist-info/top_level.txt
dagster_ext_process-1.4.17.dist-info/RECORD
