Metadata-Version: 2.1
Name: dagster-ext-process
Version: 1.4.17
Summary: Toolkit for Dagster integrations with transform logic outside of Dagster
Home-page: https://github.com/dagster-io/dagster/tree/master/python_modules/libraries/dagster-ext
Author: Dagster Labs
Author-email: hello@dagsterlabs.com
License: Apache-2.0
Classifier: Programming Language :: Python :: 3.8
Classifier: Programming Language :: Python :: 3.9
Classifier: Programming Language :: Python :: 3.10
Classifier: Programming Language :: Python :: 3.11
Classifier: License :: OSI Approved :: Apache Software License
Classifier: Operating System :: OS Independent
License-File: LICENSE
Provides-Extra: test
Requires-Dist: dagster (==1.4.17) ; extra == 'test'
Requires-Dist: boto3 ; extra == 'test'
Requires-Dist: botocore ; extra == 'test'
Requires-Dist: moto[s3,server] ; extra == 'test'
